dsigm/__init__.py
dsigm/_core.py
dsigm/_dsg.py
dsigm/_dsigm.py
dsigm/_exceptions.py
dsigm/_utils.py
dsigm/mixture/__init__.py
dsigm/mixture/_gmm.py
dsigm/mixture/_sgmm.py
tests/__init__.py
tests/test_core.py
tests/test_gmm.py
tests/test_sgmm.py
tests/test_utils.py
dsigm-0.3.1.dist-info/LICENSE
dsigm-0.3.1.dist-info/METADATA
dsigm-0.3.1.dist-info/WHEEL
dsigm-0.3.1.dist-info/top_level.txt
dsigm-0.3.1.dist-info/zip-safe
dsigm-0.3.1.dist-info/RECORD
