Metadata-Version: 2.1
Name: dsigm
Version: 0.3.1
Summary: Density-sensitive Self-stabilization of Independent Gaussian Mixtures (DSIGM) Clustering
Home-page: http://github.com/paradoxysm/dsigm
Author: paradoxysm
Author-email: paradoxysm.dev@gmail.com
License: BSD-3-Clause
Download-URL: https://github.com/paradoxysm/dsigm/archive/0.3.1.tar.gz
Keywords: clustering,python,data-science
Platform: UNKNOWN
Classifier: Development Status :: 3 - Alpha
Classifier: Intended Audience :: Developers
Classifier: Natural Language :: English
Classifier: License :: OSI Approved :: BSD License
Classifier: Operating System :: OS Independent
Classifier: Programming Language :: Python
Classifier: Programming Language :: Python :: 3
Classifier: Programming Language :: Python :: 3.4
Classifier: Programming Language :: Python :: 3.5
Classifier: Programming Language :: Python :: 3.6
Classifier: Programming Language :: Python :: 3.7
Classifier: Topic :: Software Development :: Libraries :: Python Modules
Classifier: Topic :: Scientific/Engineering :: Artificial Intelligence
Classifier: Topic :: Scientific/Engineering :: Bio-Informatics
Classifier: Topic :: Scientific/Engineering :: Information Analysis
Classifier: Intended Audience :: Science/Research
Requires-Python: >=3.4, <4
Requires-Dist: scipy
Requires-Dist: sklearn
Requires-Dist: numpy
Provides-Extra: test
Requires-Dist: pytest ; extra == 'test'
Requires-Dist: coverage ; extra == 'test'
Requires-Dist: pytest-cov ; extra == 'test'
